{
	"class" : {
		"nbBindingOf:" : "MaxLeske 3/12/2014 08:03",
		"nbLibraryNameOrHandle" : "MaxLeske 3/12/2014 08:03" },
	"instance" : {
		"refspec_direction:" : "m 3/12/2014 07:49",
		"refspec_dst:" : "m 3/12/2014 07:49",
		"refspec_dst_matches:refname:" : "m 3/12/2014 07:49",
		"refspec_force:" : "m 3/12/2014 07:49",
		"refspec_rtransform:spec:name:" : "m 3/12/2014 07:49",
		"refspec_src:" : "m 3/12/2014 07:49",
		"refspec_src_matches:refname:" : "m 3/12/2014 07:49",
		"refspec_string:" : "m 3/12/2014 07:49",
		"refspec_transform:spec:name:" : "m 3/12/2014 07:49" } }
