{
	"class" : {
		"initialize" : "JanvandeSandt 4/30/2016 20:25:31",
		"isInitialized" : "JanvandeSandt 4/30/2016 20:25:31",
		"startUp:" : "JanvandeSandt 4/30/2016 20:25:31" },
	"instance" : {
		"initializeLibGit2" : "JanvandeSandt 4/30/2016 20:25:31",
		"libgit2_features" : "JanvandeSandt 4/30/2016 20:25:31",
		"libgit2_featuresAlt" : "JanvandeSandt 4/30/2016 20:25:31",
		"libgit2_init" : "JanvandeSandt 4/30/2016 20:25:31",
		"libgit2_shutdown" : "JanvandeSandt 4/30/2016 20:25:31",
		"libgit2_version:minor:rev:" : "JanvandeSandt 4/30/2016 20:25:31",
		"macModuleName" : "JanvandeSandt 4/30/2016 20:25:31",
		"shutdownLibGit2" : "JanvandeSandt 4/30/2016 20:25:31",
		"unixModuleName" : "JanvandeSandt 4/30/2016 20:25:31",
		"version" : "JanvandeSandt 4/30/2016 20:25:31",
		"win32ModuleName" : "JanvandeSandt 4/30/2016 20:25:31" } }
