{
	"class" : {
		"enumDecl" : "MaxLeske 6/21/2015 22:47",
		"git_diff_disable_pathspec_match" : "EstebanLorenzano 2/25/2016 23:32",
		"git_diff_enable_fast_untracked_dirs" : "EstebanLorenzano 2/25/2016 23:32",
		"git_diff_force_binary" : "EstebanLorenzano 2/25/2016 23:32",
		"git_diff_force_text" : "EstebanLorenzano 2/25/2016 23:32",
		"git_diff_ignore_case" : "EstebanLorenzano 2/25/2016 23:32",
		"git_diff_ignore_filemode" : "EstebanLorenzano 2/25/2016 23:32",
		"git_diff_ignore_submodules" : "EstebanLorenzano 2/25/2016 23:32",
		"git_diff_ignore_whitespace" : "EstebanLorenzano 2/25/2016 23:32",
		"git_diff_ignore_whitespace_change" : "EstebanLorenzano 2/25/2016 23:32",
		"git_diff_ignore_whitespace_eol" : "EstebanLorenzano 2/25/2016 23:32",
		"git_diff_include_ignored" : "EstebanLorenzano 2/25/2016 23:32",
		"git_diff_include_typechange" : "EstebanLorenzano 2/25/2016 23:32",
		"git_diff_include_typechange_trees" : "EstebanLorenzano 2/25/2016 23:32",
		"git_diff_include_unmodified" : "EstebanLorenzano 2/25/2016 23:32",
		"git_diff_include_unreadable" : "EstebanLorenzano 2/25/2016 23:32",
		"git_diff_include_unreadable_as_untracked" : "EstebanLorenzano 2/25/2016 23:32",
		"git_diff_include_untracked" : "EstebanLorenzano 2/25/2016 23:32",
		"git_diff_minimal" : "EstebanLorenzano 2/25/2016 23:32",
		"git_diff_normal" : "EstebanLorenzano 2/25/2016 23:32",
		"git_diff_patience" : "EstebanLorenzano 2/25/2016 23:32",
		"git_diff_recurse_ignored_dirs" : "EstebanLorenzano 2/25/2016 23:32",
		"git_diff_recurse_untracked_dirs" : "EstebanLorenzano 2/25/2016 23:32",
		"git_diff_reverse" : "EstebanLorenzano 2/25/2016 23:32",
		"git_diff_show_binary" : "EstebanLorenzano 2/25/2016 23:32",
		"git_diff_show_unmodified" : "EstebanLorenzano 2/25/2016 23:32",
		"git_diff_show_untracked_content" : "EstebanLorenzano 2/25/2016 23:32",
		"git_diff_skip_binary_check" : "EstebanLorenzano 2/25/2016 23:32",
		"git_diff_update_index" : "EstebanLorenzano 2/25/2016 23:32",
		"patience" : "EstebanLorenzano 2/25/2016 23:32" },
	"instance" : {
		 } }
