{
	"class" : {
		"enumDecl" : "JanvandeSandt 4/14/2016 22:34:40",
		"git_blame_first_parent" : "JanVanDeSandt 4/15/2016 09:43",
		"git_blame_normal" : "JanVanDeSandt 4/15/2016 09:43",
		"git_blame_track_copies_any_commit_copies" : "JanVanDeSandt 4/15/2016 09:43",
		"git_blame_track_copies_same_commit_copies" : "JanVanDeSandt 4/15/2016 09:43",
		"git_blame_track_copies_same_commit_moves" : "JanVanDeSandt 4/15/2016 09:43",
		"git_blame_track_copies_same_file" : "JanVanDeSandt 4/15/2016 09:43" },
	"instance" : {
		 } }
