{
	"class" : {
		"nbBindingOf:" : "MaxLeske 3/12/2014 08:03",
		"nbLibraryNameOrHandle" : "MaxLeske 3/12/2014 08:03" },
	"instance" : {
		"repository_config:repo:" : "m 3/12/2014 07:49",
		"repository_detach_head:signature:reflog_message:" : "m 3/12/2014 07:49",
		"repository_discover:start_path:across_fs:ceiling_dirs:" : "m 3/12/2014 07:49",
		"repository_fetchhead_foreach:callback:payload:" : "m 3/12/2014 07:49",
		"repository_free:" : "m 3/12/2014 07:49",
		"repository_get_namespace:" : "m 3/12/2014 07:49",
		"repository_hashfile:repo:path:type:as_path:" : "m 3/12/2014 07:49",
		"repository_head:repo:" : "m 3/12/2014 07:49",
		"repository_head_detached:" : "m 3/12/2014 07:49",
		"repository_head_unborn:" : "m 3/12/2014 07:49",
		"repository_index:repo:" : "m 3/12/2014 07:49",
		"repository_init:path:is_bare:" : "m 3/12/2014 07:49",
		"repository_init_ext:repo_path:opts:" : "m 3/12/2014 07:49",
		"repository_init_init_options:version:" : "m 3/12/2014 07:49",
		"repository_is_bare:" : "m 3/12/2014 07:49",
		"repository_is_empty:" : "m 3/12/2014 07:49",
		"repository_is_shallow:" : "m 3/12/2014 07:49",
		"repository_mergehead_foreach:callback:payload:" : "m 3/12/2014 07:49",
		"repository_message:repo:" : "m 3/12/2014 07:49",
		"repository_message_remove:" : "m 3/12/2014 07:49",
		"repository_odb:repo:" : "m 3/12/2014 07:49",
		"repository_open:bare_path:" : "m 3/12/2014 07:49",
		"repository_open_bare:bare_path:" : "m 3/12/2014 07:49",
		"repository_open_ext:path:flags:ceiling_dirs:" : "m 3/12/2014 07:49",
		"repository_path:" : "m 3/12/2014 07:49",
		"repository_refdb:repo:" : "m 3/12/2014 07:49",
		"repository_set_head:refname:signature:log_message:" : "m 3/12/2014 07:49",
		"repository_set_head_detached:commitish:signature:log_message:" : "m 3/12/2014 07:49",
		"repository_set_namespace:nmspace:" : "m 3/12/2014 07:49",
		"repository_set_workdir:workdir:update_gitlink:" : "m 3/12/2014 07:49",
		"repository_state:" : "m 3/12/2014 07:49",
		"repository_state_cleanup:" : "m 3/12/2014 07:49",
		"repository_workdir:" : "m 3/12/2014 07:49",
		"repository_wrap_odb:odb:" : "m 3/12/2014 07:49" } }
