{
	"class" : {
		"freeFunctionSelector" : "JanvandeSandt 4/21/2016 22:46:08",
		"fromTree:" : "JanvandeSandt 4/21/2016 22:46:08",
		"of:fromTree:" : "JanvandeSandt 4/21/2016 22:46:08",
		"treebuilder_free:" : "JanvandeSandt 4/21/2016 22:46:08" },
	"instance" : {
		"addEntry:filename:" : "JanvandeSandt 4/21/2016 22:46:08",
		"addEntryWithId:filename:filemode:" : "JanvandeSandt 4/21/2016 22:46:08",
		"clear" : "JanvandeSandt 4/21/2016 22:46:08",
		"createNew" : "JanvandeSandt 4/21/2016 22:46:08",
		"getEntryNamed:" : "JanvandeSandt 4/21/2016 22:46:08",
		"initializeWithTree:" : "JanvandeSandt 4/21/2016 22:46:08",
		"newTree" : "JanvandeSandt 4/21/2016 22:46:08",
		"treebuilder_clear:" : "JanvandeSandt 4/21/2016 22:46:08",
		"treebuilder_get:filename:" : "JanvandeSandt 4/21/2016 22:46:08",
		"treebuilder_insert:bld:filename:id:filemode:" : "JanvandeSandt 4/21/2016 22:46:08",
		"treebuilder_new:repo:source:" : "JanvandeSandt 4/21/2016 22:46:08",
		"treebuilder_write:bld:" : "JanvandeSandt 4/21/2016 22:46:08",
		"write" : "JanvandeSandt 4/21/2016 22:46:08" } }
