{
	"class" : {
		"freeFunctionSelector" : "JanvandeSandt 4/8/2016 12:56:25",
		"new" : "JanvandeSandt 4/8/2016 12:56:25",
		"on:" : "JanvandeSandt 4/8/2016 12:56:25",
		"repository_free:" : "JanvandeSandt 4/8/2016 12:56:25" },
	"instance" : {
		"beOpen" : "JanvandeSandt 4/8/2016 12:56:25",
		"branchNames" : "JanvandeSandt 4/8/2016 12:56:25",
		"branch_lookup:repo:branch_name:branch_type:" : "JanvandeSandt 4/8/2016 12:56:25",
		"branch_next:out_type:iter:" : "JanvandeSandt 4/8/2016 12:56:25",
		"branches" : "JanvandeSandt 4/8/2016 12:56:25",
		"branchesDo:" : "JanvandeSandt 4/8/2016 12:56:25",
		"checkout:" : "JanvandeSandt 4/8/2016 12:56:25",
		"checkout_tree:treeish:opts:" : "JanvandeSandt 4/8/2016 12:56:25",
		"clone:" : "JanvandeSandt 4/8/2016 12:56:25",
		"clone:options:" : "JanvandeSandt 4/8/2016 12:56:25",
		"clone:options:to:" : "JanvandeSandt 4/8/2016 12:56:25",
		"clone:url:local_path:options:" : "JanvandeSandt 4/8/2016 12:56:25",
		"cloneHttps:" : "JanvandeSandt 4/8/2016 12:56:25",
		"cloneLocal:" : "JanvandeSandt 4/8/2016 12:56:25",
		"cloneRemote:signature:" : "JanvandeSandt 4/8/2016 12:56:25",
		"cloneRemote:signature:branch:" : "JanvandeSandt 4/8/2016 12:56:25",
		"cloneRemote:signature:branch:checkoutOptions:" : "JanvandeSandt 4/8/2016 12:56:25",
		"cloneSsh:" : "JanvandeSandt 4/8/2016 12:56:25",
		"create" : "JanvandeSandt 4/8/2016 12:56:25",
		"createBranch:force:" : "JanvandeSandt 4/8/2016 12:56:25",
		"createBranch:targetId:force:" : "JanvandeSandt 4/8/2016 12:56:25",
		"createPackForReference:" : "JanVanDeSandt 4/8/2016 14:24",
		"createTag:targetId:force:" : "JanvandeSandt 4/8/2016 12:56:25",
		"database" : "JanvandeSandt 4/8/2016 12:56:25",
		"defaultSignature" : "JanVanDeSandt 4/8/2016 14:24",
		"deleteAllLooseObjectsForReference:" : "JanvandeSandt 4/8/2016 12:56:25",
		"exists" : "JanvandeSandt 4/8/2016 12:56:25",
		"fastForward" : "JanvandeSandt 4/8/2016 12:56:25",
		"head" : "JanvandeSandt 4/8/2016 12:56:25",
		"index" : "JanvandeSandt 4/8/2016 12:56:25",
		"init" : "JanvandeSandt 4/8/2016 12:56:25",
		"initBare:" : "JanvandeSandt 4/8/2016 12:56:25",
		"initializeOn:" : "JanvandeSandt 4/8/2016 12:56:25",
		"isBare" : "JanvandeSandt 4/8/2016 12:56:25",
		"isDirty:" : "JanvandeSandt 4/8/2016 12:56:25",
		"isEmpty" : "JanvandeSandt 4/8/2016 12:56:25",
		"isInitialized" : "JanvandeSandt 4/8/2016 12:56:25",
		"isOpen" : "JanvandeSandt 4/8/2016 12:56:25",
		"isProperRepository" : "JanvandeSandt 4/8/2016 12:56:25",
		"lookup:" : "JanvandeSandt 4/8/2016 12:56:25",
		"lookupBranch:" : "JanvandeSandt 4/8/2016 12:56:25",
		"master" : "JanvandeSandt 4/8/2016 12:56:25",
		"objectPrintOn:" : "JanvandeSandt 4/8/2016 12:56:25",
		"open" : "JanvandeSandt 4/8/2016 12:56:25",
		"packHead" : "JanvandeSandt 4/8/2016 12:56:25",
		"reference_lookup:repo:shorthand:" : "JanvandeSandt 4/8/2016 12:56:25",
		"references" : "JanvandeSandt 4/8/2016 12:56:25",
		"repositoryReference" : "JanvandeSandt 4/8/2016 12:56:25",
		"repositoryReference:" : "JanvandeSandt 4/8/2016 12:56:25",
		"repository_head:of:" : "JanvandeSandt 4/8/2016 12:56:25",
		"repository_index:repo:" : "JanvandeSandt 4/8/2016 12:56:25",
		"repository_init:path:is_bare:" : "JanvandeSandt 4/8/2016 12:56:25",
		"repository_is_bare:" : "JanvandeSandt 4/8/2016 12:56:25",
		"repository_is_empty:" : "JanvandeSandt 4/8/2016 12:56:25",
		"repository_odb:repo:" : "JanvandeSandt 4/8/2016 12:56:25",
		"repository_open:bare_path:" : "JanvandeSandt 4/8/2016 12:56:25",
		"repository_open_ext:path:flags:ceiling_dirs:" : "JanvandeSandt 4/8/2016 12:56:25",
		"repository_set_head:refname:log_message:" : "JanvandeSandt 4/8/2016 12:56:25",
		"repository_workdir:" : "JanvandeSandt 4/8/2016 12:56:25",
		"revparse:" : "JanvandeSandt 4/8/2016 12:56:25",
		"revparse_single:repo:spec:" : "JanvandeSandt 4/8/2016 12:56:25",
		"signature_default:repo:" : "JanVanDeSandt 4/8/2016 14:24",
		"tag_list:repo:" : "JanvandeSandt 4/8/2016 12:56:25",
		"tags" : "JanvandeSandt 4/8/2016 12:56:25",
		"workingDirectory" : "JanvandeSandt 4/8/2016 12:56:25",
		"workingDirectoryName" : "JanvandeSandt 4/8/2016 12:56:25" } }
